MANIFEST.in
README.txt
setup.cfg
setup.py
pdfcat/__init__.py
pdfcat/pdfcat.py
pdfcat.egg-info/PKG-INFO
pdfcat.egg-info/SOURCES.txt
pdfcat.egg-info/dependency_links.txt
pdfcat.egg-info/entry_points.txt
pdfcat.egg-info/not-zip-safe
pdfcat.egg-info/top_level.txt