Metadata-Version: 1.0
Name: pdfcat
Version: 1.0
Summary: pdf concatenation tool
Home-page: https://svn.plonegov.org/pdfcat
Author: atReal
Author-email: contact@atreal.net
License: GPL
Platform: UNKNOWN
